<beans xmlns="http://www.springframework.org/schema/beans"
	xmlns:xsi="http://www.w3.org/2001/XMLSchema-instance"
	xsi:schemaLocation="http://www.springframework.org/schema/beans
	http://www.springframework.org/schema/beans/spring-beans-3.0.xsd">
 
	<bean id="mainDAO" class="bephit.dao.MainDAO">
		<property name="dataSource" ref="dataSource" />
	</bean>

	<bean id="patientDAO" class="bephit.dao.PatientDAO">
	<property name="dataSource" ref="dataSource" />
	</bean>

	<bean id="AutoaccidentDAO" class="bephit.dao.AutoaccidentDAO">
		<property name="dataSource" ref="dataSource" />
	</bean>

	<bean id="AssignmentDAO" class="bephit.dao.AssignmentDAO">
		<property name="dataSource" ref="dataSource" />
	</bean>
	<bean id="TreatDAO" class="bephit.dao.TreatDAO">
		<property name="dataSource" ref="dataSource" />
	</bean>
	<bean id="TreatMinorDAO" class="bephit.dao.TreatMinorDAO">
		<property name="dataSource" ref="dataSource" />
	</bean>
	<bean id="MedicalDAO" class="bephit.dao.MedicalDAO">
		<property name="dataSource" ref="dataSource" />
	</bean>
	<bean id="ScreenDAO" class="bephit.dao.ScreenDAO">
		<property name="dataSource" ref="dataSource" />
	</bean>
	<bean id="HippaDAO" class="bephit.dao.HippaDAO">
		<property name="dataSource" ref="dataSource" />
	</bean>

    <bean id="WorkaccidentDAO" class="bephit.dao.WorkaccidentDAO">
    	<property name="dataSource" ref="dataSource" />
    </bean>
<bean id="InsuranceinformationDAO" class="bephit.dao.InsuranceinformationDAO">
    	<property name="dataSource" ref="dataSource" />
    </bean>
    <bean id="InsuranceverificationDAO" class="bephit.dao.InsuranceverificationDAO">
    	<property name="dataSource" ref="dataSource" />
    </bean>
     <bean id="InsuranceplanDAO" class="bephit.dao.InsuranceplanDAO">
    	<property name="dataSource" ref="dataSource" />
    </bean>
    <bean id="HardshipagreementDAO" class="bephit.dao.HardshipagreementDAO">
    	<property name="dataSource" ref="dataSource" />
    </bean>
    <bean id="StaffchecklistDAO" class="bephit.dao.StaffchecklistDAO">
    	<property name="dataSource" ref="dataSource" />
    </bean>
    <bean id="SignupDAO" class="bephit.dao.SignupDAO">
    	<property name="dataSource" ref="dataSource" />
    </bean>
    
     <bean id="DoctorsignupDAO" class="bephit.dao.DoctorsignupDAO">
    	<property name="dataSource" ref="dataSource" />
    </bean>
<bean id="PhysicalexamDAO" class="bephit.dao.PhysicalexamDAO">
    	<property name="dataSource" ref="dataSource" />
    </bean>
   <bean id="HamiltonchiropracticDAO" class="bephit.dao.HamiltonchiropracticDAO">
    	<property name="dataSource" ref="dataSource" />
    </bean>
    <bean id="MoretestDAO" class="bephit.dao.MoretestDAO">
    	<property name="dataSource" ref="dataSource" />
    </bean>

 <bean id="RadiologicReportDAO" class="bephit.dao.RadiologicReportDAO">
    	<property name="dataSource" ref="dataSource" />
    </bean>
    <bean id="DoctorsearchDAO" class="bephit.dao.DoctorsearchDAO">
    	<property name="dataSource" ref="dataSource" />
    </bean>
 <bean id="SoapnotesDAO" class="bephit.dao.SoapnotesDAO">
    	<property name="dataSource" ref="dataSource" />
    </bean>
     <bean id="HipexamDAO" class="bephit.dao.HipexamDAO">
    	<property name="dataSource" ref="dataSource" />
    </bean>
 <bean id="LumbopelvicexamDAO" class="bephit.dao.LumbopelvicexamDAO">
    	<property name="dataSource" ref="dataSource" />
    </bean> 
    <bean id="FootexamDAO" class="bephit.dao.FootexamDAO">
    	<property name="dataSource" ref="dataSource" />
    </bean> 
    <bean id="KneeexamDAO" class="bephit.dao.KneeexamDAO">
    	<property name="dataSource" ref="dataSource" />
    </bean>     
     <bean id="ShoulderexamDAO" class="bephit.dao.ShoulderexamDAO">
    	<property name="dataSource" ref="dataSource" />
    </bean>
    <bean id="WristexamDAO" class="bephit.dao.WristexamDAO">
    	<property name="dataSource" ref="dataSource" />
    </bean>
    <bean id="CervicalexamDAO" class="bephit.dao.CervicalexamDAO">
    	<property name="dataSource" ref="dataSource" />
    </bean>
    <bean id="ElbowexamDAO" class="bephit.dao.ElbowexamDAO">
    	<property name="dataSource" ref="dataSource" />
    </bean>
    <bean id="ThoracicexamDAO" class="bephit.dao.ThoracicexamDAO">
    	<property name="dataSource" ref="dataSource" />
    </bean>
    <bean id="DcfeeslipDAO" class="bephit.dao.DcfeeslipDAO">
    	<property name="dataSource" ref="dataSource" />
    </bean> 
         <bean id="SymptomDAO" class="bephit.dao.SymptomDAO">
    	<property name="dataSource" ref="dataSource" />
    </bean>
    <bean id="ManualtherapyDAO" class="bephit.dao.ManualtherapyDAO">
    	<property name="dataSource" ref="dataSource" />
    </bean>   
    <bean id="LowbackDAO" class="bephit.dao.LowbackDAO">
           <property name="dataSource" ref="dataSource" />
   </bean>
    <bean id="WristindexDAO" class="bephit.dao.WristindexDAO">
           <property name="dataSource" ref="dataSource" />
   </bean> 
    <bean id="NeckindexDAO" class="bephit.dao.NeckindexDAO">
           <property name="dataSource" ref="dataSource" />
   </bean> 
    <bean id="HipquestionnaireDAO" class="bephit.dao.HipquestionnaireDAO">
           <property name="dataSource" ref="dataSource" />

   </bean>   
   <bean id="DutiesunderDAO" class="bephit.dao.DutiesunderDAO">
           <property name="dataSource" ref="dataSource" />
   </bean>

    <bean id="FootquestionnarieDAO" class="bephit.dao.FootquestionnarieDAO">
           <property name="dataSource" ref="dataSource" />
   </bean>
   <bean id="ShoulderpainscoreDAO" class="bephit.dao.ShoulderpainscoreDAO">
           <property name="dataSource" ref="dataSource" />
   </bean>

   <bean id="OswestryDAO" class="bephit.dao.OswestryDAO">
           <property name="dataSource" ref="dataSource" />
   </bean>
   <bean id="QuadraplevisualDAO" class="bephit.dao.QuadraplevisualDAO">
           <property name="dataSource" ref="dataSource" />
   </bean>
   
   <bean id="CopyofrequestDAO" class="bephit.dao.CopyofrequestDAO">
           <property name="dataSource" ref="dataSource" />
   </bean> 
   
   <bean id="PerrychiropracticDAO" class="bephit.dao.PerrychiropracticDAO">
           <property name="dataSource" ref="dataSource" />
   </bean> 
    <bean id="UpdateletterDAO" class="bephit.dao.UpdateletterDAO">
           <property name="dataSource" ref="dataSource" />
   </bean>
   <bean id="NarrativereportDAO" class="bephit.dao.NarrativereportDAO">
           <property name="dataSource" ref="dataSource" />
   </bean> 
   <bean id="XrayDAO" class="bephit.dao.XrayDAO">
           <property name="dataSource" ref="dataSource" />
   </bean>


<bean id="FormbillDAO" class="bephit.dao.FormbillDAO">
           <property name="dataSource" ref="dataSource" />
   </bean>

 <bean id="LetterofprotectionDAO" class="bephit.dao.LetterofprotectionDAO">
           <property name="dataSource" ref="dataSource" />
   </bean>
  <bean id="RequestfordemandDAO" class="bephit.dao.RequestfordemandDAO">
           <property name="dataSource" ref="dataSource" />
   </bean>
   <bean id="LettertopatientsDAO" class="bephit.dao.LettertopatientsDAO">
           <property name="dataSource" ref="dataSource" />
   </bean>
    <bean id="FaxcoverDAO" class="bephit.dao.FaxcoverDAO">
           <property name="dataSource" ref="dataSource" />
   </bean>
    <bean id="PimedpayDAO" class="bephit.dao.PimedpayDAO">
           <property name="dataSource" ref="dataSource" />
   </bean>
   <bean id="WorkschoolDAO" class="bephit.dao.WorkschoolDAO">
           <property name="dataSource" ref="dataSource" />
   </bean>
   <bean id="ReturntoschoolDAO" class="bephit.dao.ReturntoschoolDAO">
           <property name="dataSource" ref="dataSource" />
   </bean>
   <bean id="Patientattorney1DAO" class="bephit.dao.Patientattorney1DAO">
           <property name="dataSource" ref="dataSource" />
   </bean>
   <bean id="ResponseattorneyDAO" class="bephit.dao.ResponseattorneyDAO">
           <property name="dataSource" ref="dataSource" />
   </bean>   
   <bean id="NoticeassignmentDAO" class="bephit.dao.NoticeassignmentDAO">
           <property name="dataSource" ref="dataSource" />
   </bean>  
   
</beans>